blocklist_aggregator/__init__.py
blocklist_aggregator/aggregator.py
blocklist_aggregator/blocklist.conf
blocklist_aggregator-1.4.2.dist-info/licenses/LICENSE
blocklist_aggregator-1.4.2.dist-info/METADATA
blocklist_aggregator-1.4.2.dist-info/WHEEL
blocklist_aggregator-1.4.2.dist-info/top_level.txt
blocklist_aggregator-1.4.2.dist-info/RECORD
