Metadata-Version: 2.4
Name: blocklist_aggregator
Version: 1.4.2
Summary: Domains blocklist aggregator
Home-page: https://github.com/dmachard/blocklist-aggregator
Author: Denis MACHARD
Author-email: d.machard@gmail.com
Keywords: blocklist aggregator domains dns blacklist whitelist
Platform: any
Classifier: License :: OSI Approved :: MIT License
Classifier: Programming Language :: Python :: 3
Classifier: Operating System :: OS Independent
Classifier: Topic :: Software Development :: Libraries
License-File: LICENSE
Requires-Dist: pyyaml
Requires-Dist: requests
Requires-Dist: pure-cdb
Requires-Dist: httpx[http2]
Dynamic: author
Dynamic: author-email
Dynamic: classifier
Dynamic: description
Dynamic: description-content-type
Dynamic: home-page
Dynamic: keywords
Dynamic: license-file
Dynamic: platform
Dynamic: requires-dist
Dynamic: summary
